pvleopard/LICENSE
pvleopard/__init__.py
pvleopard/_factory.py
pvleopard/_leopard.py
pvleopard/_util.py
pvleopard/lib/common/leopard_params.pv
pvleopard/lib/linux/x86_64/libpv_leopard.so
pvleopard/lib/mac/arm64/libpv_leopard.dylib
pvleopard/lib/mac/x86_64/libpv_leopard.dylib
pvleopard/lib/raspberry-pi/cortex-a53/libpv_leopard.so
pvleopard/lib/raspberry-pi/cortex-a53-aarch64/libpv_leopard.so
pvleopard/lib/raspberry-pi/cortex-a72/libpv_leopard.so
pvleopard/lib/raspberry-pi/cortex-a72-aarch64/libpv_leopard.so
pvleopard/lib/raspberry-pi/cortex-a76/libpv_leopard.so
pvleopard/lib/raspberry-pi/cortex-a76-aarch64/libpv_leopard.so
pvleopard/lib/windows/amd64/libpv_leopard.dll
pvleopard/lib/windows/amd64/pv_ypu_impl_cuda.dll
pvleopard/lib/windows/arm64/libpv_leopard.dll
pvleopard-3.0.0.dist-info/METADATA
pvleopard-3.0.0.dist-info/WHEEL
pvleopard-3.0.0.dist-info/top_level.txt
pvleopard-3.0.0.dist-info/RECORD
